zen_mode/__init__.py
zen_mode/claude.py
zen_mode/cli.py
zen_mode/config.py
zen_mode/context.py
zen_mode/core.py
zen_mode/exceptions.py
zen_mode/files.py
zen_mode/git.py
zen_mode/implement.py
zen_mode/judge.py
zen_mode/linter.py
zen_mode/plan.py
zen_mode/ratchet.py
zen_mode/scout.py
zen_mode/swarm.py
zen_mode/triage.py
zen_mode/verify.py
zen_mode/defaults/CLAUDE.md
zen_mode/defaults/__init__.py
zen_mode-1.1.1.dist-info/METADATA
zen_mode-1.1.1.dist-info/WHEEL
zen_mode-1.1.1.dist-info/entry_points.txt
zen_mode-1.1.1.dist-info/licenses/LICENSE
zen_mode-1.1.1.dist-info/RECORD
