Metadata-Version: 2.4
Name: zen-mode
Version: 1.1.1
Summary: Minimalist autonomous agent runner
Project-URL: Homepage, https://github.com/HakAl/zen
Project-URL: Repository, https://github.com/HakAl/zen
Author: Zen Mode Contributors
License-Expression: MIT
License-File: LICENSE
Keywords: agent,ai,automation,claude
Classifier: Development Status :: 5 - Production/Stable
Classifier: Environment :: Console
Classifier: Intended Audience :: Developers
Classifier: License :: OSI Approved :: MIT License
Classifier: Programming Language :: Python :: 3
Classifier: Programming Language :: Python :: 3.9
Classifier: Programming Language :: Python :: 3.10
Classifier: Programming Language :: Python :: 3.11
Classifier: Programming Language :: Python :: 3.12
Classifier: Topic :: Software Development :: Build Tools
Requires-Python: >=3.9
Provides-Extra: dev
Requires-Dist: pytest>=7.0; extra == 'dev'
